YouTubeCommentAnalysis/CommentCorpus.py
YouTubeCommentAnalysis/EmotionAnalysis.py
YouTubeCommentAnalysis/FileExIm.py
YouTubeCommentAnalysis/NRC-Emotion-Lexicon.csv
YouTubeCommentAnalysis/TextProcessing.py
YouTubeCommentAnalysis/WordAssociation.py
YouTubeCommentAnalysis/__init__.py
YouTubeCommentAnalysis-0.0.4.dist-info/LICENSE
YouTubeCommentAnalysis-0.0.4.dist-info/METADATA
YouTubeCommentAnalysis-0.0.4.dist-info/WHEEL
YouTubeCommentAnalysis-0.0.4.dist-info/top_level.txt
YouTubeCommentAnalysis-0.0.4.dist-info/RECORD
