Metadata-Version: 2.1
Name: YouTubeCommentAnalysis
Version: 0.0.4
Summary: YouTube Comment Analysis
Home-page: https://github.com/nguyenha1910/YouTubeCommentAnalysis
Author: Nguyen Ha, Shuo Niu
Author-email: nguyenhbhcm@gmail.com
License: MIT license
Platform: UNKNOWN
Classifier: License :: OSI Approved :: MIT License
Classifier: Programming Language :: Python :: 3.7
Requires-Python: >=3.6
License-File: LICENSE
Requires-Dist: beautifulsoup4
Requires-Dist: nltk
Requires-Dist: emoji
Requires-Dist: gensim
Requires-Dist: pandas
Requires-Dist: importlib-resources ; python_version < "3.7"
